target_redshift/__init__.py
target_redshift/redshift.py
target_redshift/s3.py
target_redshift-0.2.4.dist-info/LICENSE
target_redshift-0.2.4.dist-info/METADATA
target_redshift-0.2.4.dist-info/WHEEL
target_redshift-0.2.4.dist-info/entry_points.txt
target_redshift-0.2.4.dist-info/top_level.txt
target_redshift-0.2.4.dist-info/RECORD
