Metadata-Version: 2.1
Name: target-redshift
Version: 0.2.4
Summary: Singer.io target for loading data into redshift
Home-page: https://github.com/datamill-co/target-redshift
Author: datamill
License: UNKNOWN
Platform: UNKNOWN
Classifier: Programming Language :: Python :: 3 :: Only
Requires-Dist: boto3 (<1.10.0,>=1.9.205)
Requires-Dist: singer-target-postgres (==0.2.4)
Requires-Dist: urllib3 (==1.25.9)
Provides-Extra: tests
Requires-Dist: chance (==0.110) ; extra == 'tests'
Requires-Dist: Faker (==4.0.3) ; extra == 'tests'
Requires-Dist: pytest (==5.4.1) ; extra == 'tests'
